bragg/__init__.py
bragg/py.typed
bragg-0.0.0.dist-info/WHEEL
bragg-0.0.0.dist-info/METADATA
bragg-0.0.0.dist-info/RECORD
